Workbook

Sheet 00_guide
A1: 日本子公司6个月交易预估报告（TINPASS / 日本账户入金）
A3: 本表格用于事先说明：日本子公司从日本交易对手收款后，向 TINPASS 日本账户入金，并据此向代表支付 USDT，以便税务与 AML 审查。 填写主体：日本子公司 期间：自8月起6个月（8月–次年1月） 币种：JPY（在黄色单元格填写日均规模，周/月由公式自动合计） 步骤 1) 01_volume — 仅填每月日均（周=日×7，月=日×当月天数） 2) 02_daily — 可选按日 3) 03_nature — 资金性质 4) 04_docs — 个人/法人文件 5) 保存后在 TINPASS USDT 申请时上传
A20: 黄=填写 / 蓝=自动计算 / 绿=6个月合计

Sheet 01_volume
A1: 6个月交易规模预估（填写日均 → 周/月自动合计）
A3: 月 | B3: 当月天数 | C3: 日均规模 (JPY) ※填写 | D3: 周规模 (JPY)=日×7 | E3: 月规模 (JPY)=日×天数 | F3: 备注（笔数/对手数） | G3: 资金性质代码 | H3: 填写人确认
A4: 2026-08 | B4: 31 | D4: =IF(C4="","",C4*7) | E4: =IF(C4="","",C4*B4)
A5: 2026-09 | B5: 30 | D5: =IF(C5="","",C5*7) | E5: =IF(C5="","",C5*B5)
A6: 2026-10 | B6: 31 | D6: =IF(C6="","",C6*7) | E6: =IF(C6="","",C6*B6)
A7: 2026-11 | B7: 30 | D7: =IF(C7="","",C7*7) | E7: =IF(C7="","",C7*B7)
A8: 2026-12 | B8: 31 | D8: =IF(C8="","",C8*7) | E8: =IF(C8="","",C8*B8)
A9: 2027-01 | B9: 31 | D9: =IF(C9="","",C9*7) | E9: =IF(C9="","",C9*B9)
A10: 6个月合计 | B10: =SUM(B4:B9) | C10: =SUM(C4:C9) | D10: =SUM(D4:D9) | E10: =SUM(E4:E9) | F10: E列月合计为日本账户计划入金总额基准。
A12: 日均平均 | B12: =IF(COUNT(C4:C9)=0,"",AVERAGE(C4:C9))
A13: 月均平均 | B13: =IF(COUNT(E4:E9)=0,"",AVERAGE(E4:E9))
A15: 填写法人名称
A16: 代表人 | C16: 印章/签名
A17: 填写日
A19: 周=日×7，月=日×当月天数。周末/假日无交易请在 02_daily 按日填写。

Sheet 02_daily
A1: 按日预估（可选）— 月合计与 01_volume 核对
A3: 日期 | B3: 星期 | C3: 日规模(JPY) ※填写 | D3: 周起始(一) | E3: 该周合计 | F3: 月
A4: 46235 | B4: 六 | D4: =A4-WEEKDAY(A4,2)+1 | E4: =SUMIF($D$4:$D$187,D4,$C$4:$C$187) | F4: =TEXT(A4,"YYYY-MM")
A5: 46236 | B5: 日 | D5: =A5-WEEKDAY(A5,2)+1 | E5: =SUMIF($D$4:$D$187,D5,$C$4:$C$187) | F5: =TEXT(A5,"YYYY-MM")
A6: 46237 | B6: 一 | D6: =A6-WEEKDAY(A6,2)+1 | E6: =SUMIF($D$4:$D$187,D6,$C$4:$C$187) | F6: =TEXT(A6,"YYYY-MM")
A7: 46238 | B7: 二 | D7: =A7-WEEKDAY(A7,2)+1 | E7: =SUMIF($D$4:$D$187,D7,$C$4:$C$187) | F7: =TEXT(A7,"YYYY-MM")
A8: 46239 | B8: 三 | D8: =A8-WEEKDAY(A8,2)+1 | E8: =SUMIF($D$4:$D$187,D8,$C$4:$C$187) | F8: =TEXT(A8,"YYYY-MM")
A9: 46240 | B9: 四 | D9: =A9-WEEKDAY(A9,2)+1 | E9: =SUMIF($D$4:$D$187,D9,$C$4:$C$187) | F9: =TEXT(A9,"YYYY-MM")
A10: 46241 | B10: 五 | D10: =A10-WEEKDAY(A10,2)+1 | E10: =SUMIF($D$4:$D$187,D10,$C$4:$C$187) | F10: =TEXT(A10,"YYYY-MM")
A11: 46242 | B11: 六 | D11: =A11-WEEKDAY(A11,2)+1 | E11: =SUMIF($D$4:$D$187,D11,$C$4:$C$187) | F11: =TEXT(A11,"YYYY-MM")
A12: 46243 | B12: 日 | D12: =A12-WEEKDAY(A12,2)+1 | E12: =SUMIF($D$4:$D$187,D12,$C$4:$C$187) | F12: =TEXT(A12,"YYYY-MM")
A13: 46244 | B13: 一 | D13: =A13-WEEKDAY(A13,2)+1 | E13: =SUMIF($D$4:$D$187,D13,$C$4:$C$187) | F13: =TEXT(A13,"YYYY-MM")
A14: 46245 | B14: 二 | D14: =A14-WEEKDAY(A14,2)+1 | E14: =SUMIF($D$4:$D$187,D14,$C$4:$C$187) | F14: =TEXT(A14,"YYYY-MM")
A15: 46246 | B15: 三 | D15: =A15-WEEKDAY(A15,2)+1 | E15: =SUMIF($D$4:$D$187,D15,$C$4:$C$187) | F15: =TEXT(A15,"YYYY-MM")
... A187: 46418 | B187: 日 | D187: =A187-WEEKDAY(A187,2)+1 | E187: =SUMIF($D$4:$D$187,D187,$C$4:$C$187) | F187: =TEXT(A187,"YYYY-MM")
A189: 按月合计 (02_daily)
A190: 2026-08 | B190: =SUMIF($F$4:$F$187,A190,$C$4:$C$187) | C190: 01_volume 月计 | D190: =VLOOKUP(A190,'01_volume'!A4:E9,5,FALSE) | E190: 差额 | F190: =IF(B190=0,"(未按日填写)",B190-D190)
A191: 2026-09 | B191: =SUMIF($F$4:$F$187,A191,$C$4:$C$187) | C191: 01_volume 月计 | D191: =VLOOKUP(A191,'01_volume'!A4:E9,5,FALSE) | E191: 差额 | F191: =IF(B191=0,"(未按日填写)",B191-D191)
A192: 2026-10 | B192: =SUMIF($F$4:$F$187,A192,$C$4:$C$187) | C192: 01_volume 月计 | D192: =VLOOKUP(A192,'01_volume'!A4:E9,5,FALSE) | E192: 差额 | F192: =IF(B192=0,"(未按日填写)",B192-D192)
A193: 2026-11 | B193: =SUMIF($F$4:$F$187,A193,$C$4:$C$187) | C193: 01_volume 月计 | D193: =VLOOKUP(A193,'01_volume'!A4:E9,5,FALSE) | E193: 差额 | F193: =IF(B193=0,"(未按日填写)",B193-D193)
A194: 2026-12 | B194: =SUMIF($F$4:$F$187,A194,$C$4:$C$187) | C194: 01_volume 月计 | D194: =VLOOKUP(A194,'01_volume'!A4:E9,5,FALSE) | E194: 差额 | F194: =IF(B194=0,"(未按日填写)",B194-D194)
A195: 2027-01 | B195: =SUMIF($F$4:$F$187,A195,$C$4:$C$187) | C195: 01_volume 月计 | D195: =VLOOKUP(A195,'01_volume'!A4:E9,5,FALSE) | E195: 差额 | F195: =IF(B195=0,"(未按日填写)",B195-D195)

Sheet 03_nature
A1: 交易预估性质 — 子公司收取并汇入 TINPASS 日本账户的资金
A3: 代码 | B3: 资金性质 | C3: 对手类型（个人/法人） | D3: 行业/关系 | E3: 合同/依据 | F3: 预计占比(%) | G3: 备注（税/预提）
A4: A | B4: 日本国内货款（商品） | C4: 法人或个体户 | E4: 买卖合同/发票/交货 | G4: 消费税
A5: B | B5: 服务/咨询费 | C5: 法人或个人 | E5: 委托合同/发票 | G5: 预提税
A6: C | B6: 特许权/许可 | C6: 法人 | E6: 许可合同 | G6: 使用费预提
A7: D | B7: 借款回收/集团贷款 | C7: 关联公司 | E7: 借贷合同/还款表 | G7: 利息/转让定价
A8: E | B8: 增资/出资 | C8: 股东 | E8: 股东会纪要/缴款证明 | G8: 资本交易
A9: F | B9: 其他（必须具体说明） | G9: 性质不明不得入金
A11: 占比合计(%) — 须为100 | B11: =SUM(F4:F9)
A13: 汇入 TINPASS 日本账户的资金流
A14: ① 日本交易对手 → 日本子公司账户（收款时保管 KYC、合同、发票） ② 日本子公司 → TINPASS 指定日本账户（汇款人名=子公司） ③ TINPASS → 向代表人钱包支付 USDT 各阶段合同、汇款明细、收据须备日本国税调查。

Sheet 04_docs
A1: 提交与保管文件清单（个人/法人）
A3: 分类 | B3: 阶段 | C3: 文件名 (JP) | D3: 文件名 (本地) | E3: 个人 | F3: 法人 | G3: 保管期限 | H3: TINPASS 申请时上传
A4: 身份 | B4: 子公司KYC | C4: 本人確認書類（免許証/在留/パスポート） | D4: 身份证明 | E4: 必须 | F4: 代表人必须 | G4: 交易结束+7年 | H4: 副本
A5: 身份 | B5: 子公司KYC | C5: 登記事項証明書・定款 | D5: 登记/章程 | E5: 不适用 | F5: 必须 | G5: 保持最新 | H5: 副本
A6: 身份 | B6: 子公司KYC | C6: 実質的支配者申告 | D6: 实际控制人 | E6: 不适用 | F6: 必须 | G6: 变更时更新 | H6: 副本
A7: 收款 | B7: 对手→子公司 | C7: 取引契約書 | D7: 交易合同 | E7: 必须 | F7: 必须 | G7: 交易结束+7年 | H7: 摘要或全文
A8: 收款 | B8: 对手→子公司 | C8: 請求書・納品書 | D8: 发票/交货单 | E8: 必须 | F8: 必须 | G8: 7年 | H8: 相关交易
A9: 收款 | B9: 对手→子公司 | C9: 相手方本人確認/登記 | D9: 对手身份/登记 | E9: 个人对手时 | F9: 法人对手时 | G9: 7年 | H9: 要求时
A10: 收款 | B10: 对手→子公司 | C10: 振込依頼人名が確認できる入金明細 | D10: 入账明细（汇款人） | E10: 必须 | F10: 必须 | G10: 7年 | H10: 建议
A11: 汇出 | B11: 子公司→TINPASS | C11: 取締役決定・送金稟議 | D11: 董事会/汇款审批 | E11: 不适用 | F11: 必须 | G11: 7年 | H11: 必须
A12: 汇出 | B12: 子公司→TINPASS | C12: 送金依頼書・振込明細書 | D12: 汇款申请/明细 | E12: 必须 | F12: 必须 | G12: 7年 | H12: 入金后另行
A13: 汇出 | B13: 子公司→TINPASS | C13: 本 6か月予定報告書 | D13: 本6个月预估报告 | E13: 必须 | F13: 必须 | G13: 当年+6年 | H13: 必须
A14: 税务 | B14: 国税 | C14: 総勘定元帳・現金出納 | D14: 总账/出纳 | E14: 简易账 | F14: 必须 | G14: 7年(法人税) | H14: 无需上传·保管
... A18: 加密资产 | B18: USDT领取 | C18: USDT受領後の帳簿記載 | D18: 领取后记账 | E18: 必须 | F18: 必须 | G18: 7年 | H18: 无需上传·保管
A21: 个人：代表为个体或从个人收款时请核对照栏。 法人：无登记、实际控制人、董事会决议不得向 TINPASS 日本账户入金。 保管：日本法人税账簿7年。
